reddutils/__init__.py
reddutils/example.py
reddutils/correlator/__init__.py
reddutils/exodus/__init__.py
reddutils/exodus/data/images/earth.png
reddutils/exodus/data/images/jupiter.png
reddutils/exodus/data/images/mars.png
reddutils/exodus/data/images/mercury.png
reddutils/exodus/data/images/neptune.png
reddutils/exodus/data/images/saturn.png
reddutils/exodus/data/images/uranus.png
reddutils/exodus/data/images/venus.png
reddutils/exodus/data/tables/exo_list.csv
reddutils/exodus/data/tables/good_reads_epeu.dat
reddutils/exodus/data/tables/good_reads_eporg.dat
reddutils/exodus/data/tables/good_reads_nasa.dat
reddutils/exodus/data/tables/good_reads_offline.dat
reddutils/exodus/data/tables/ss_list_epeu.csv
reddutils/exodus/data/tables/ss_list_eporg.csv
reddutils/exodus/data/tables/ss_list_nasa.csv
reddutils/exodus/data/tables/ss_list_offline.csv
reddutils/fourier/__init__.py
reddutils/owoifier/__init__.py
reddutils/periodogram/__init__.py
reddutils-1.0.7.dist-info/LICENSE
reddutils-1.0.7.dist-info/METADATA
reddutils-1.0.7.dist-info/WHEEL
reddutils-1.0.7.dist-info/top_level.txt
reddutils-1.0.7.dist-info/RECORD
