Metadata-Version: 2.1
Name: reddutils
Version: 1.0.7
Summary: Small package for personal use
Author: ReddTea
Author-email: redd@tea.com
Classifier: Programming Language :: Python :: 3
Classifier: License :: OSI Approved :: MIT License
Classifier: Operating System :: OS Independent
Requires-Python: >=3.6
License-File: LICENSE
Requires-Dist: numpy
Requires-Dist: matplotlib >=3.5.1
Requires-Dist: PyAstronomy
Requires-Dist: gatspy
Requires-Dist: ipywidgets
Requires-Dist: tabulate
